MANIFEST.in
README.rst
setup.py
django_s3_cache.egg-info/PKG-INFO
django_s3_cache.egg-info/SOURCES.txt
django_s3_cache.egg-info/dependency_links.txt
django_s3_cache.egg-info/not-zip-safe
django_s3_cache.egg-info/requires.txt
django_s3_cache.egg-info/top_level.txt
s3cache/__init__.py
s3cache/tests.py