Metadata-Version: 1.0
Name: django-s3-cache
Version: 1.4.2
Summary: Amazon Simple Storage Service (S3) cache backend for Django
Home-page: https://github.com/atodorov/django-s3-cache
Author: Alexander Todorov
Author-email: atodorov@nospam.otb.bg
License: BSD
Keywords: Amazon,S3,Django,cache
Platform: UNKNOWN
Classifier: Development Status :: 5 - Production/Stable
Classifier: Environment :: Web Environment
Classifier: Intended Audience :: Developers
Classifier: License :: OSI Approved :: BSD License
Classifier: Operating System :: OS Independent
Classifier: Programming Language :: Python
Classifier: Framework :: Django
